MANIFEST.in
README.md
requirements.txt
setup.cfg
setup.py
versioneer.py
HiCAssembler.egg-info/PKG-INFO
HiCAssembler.egg-info/SOURCES.txt
HiCAssembler.egg-info/dependency_links.txt
HiCAssembler.egg-info/not-zip-safe
HiCAssembler.egg-info/requires.txt
HiCAssembler.egg-info/top_level.txt
bin/assemble
bin/plotScaffoldInteractive
bin/plotScaffoldsHiC
hicassembler/HiCAssembler.py
hicassembler/HiCAssembler_working_copy.py
hicassembler/PathGraph.py
hicassembler/Scaffolds.py
hicassembler/__init__.py
hicassembler/_version.py
hicassembler/hicassembler_attic.py
hicassembler/parserCommon.py
hicassembler/plotScaffoldInteractive.py
hicassembler/plotScaffoldsHiC.py