Metadata-Version: 1.2
Name: HiCAssembler
Version: 1.1.1
Summary: Hi-C guided genome assembly
Home-page: https://github.com/maxplanck-ie/HiCAssembler
Author: Fidel Ramírez, Gina Renschler, Gautier Richard
Author-email: fidel.ramirez@gmail.com
License: BSD
Platform: UNKNOWN
Classifier: Development Status :: 5 - Production/Stable
Classifier: Environment :: Console
Classifier: Framework :: Jupyter
Classifier: Intended Audience :: Developers
Classifier: Intended Audience :: Science/Research
Classifier: Natural Language :: English
Classifier: Operating System :: MacOS :: MacOS X
Classifier: Operating System :: Microsoft :: Windows
Classifier: Operating System :: POSIX :: Linux
Classifier: Programming Language :: Python :: 3
Classifier: Programming Language :: Python :: 3.5
Classifier: Programming Language :: Python :: 3.6
Classifier: Topic :: Scientific/Engineering :: Bio-Informatics
Requires-Python: >=2.7
